agent_tasks/__init__.py
agent_tasks/prompt_template.j2
agent_tasks/prompts.py
agent_tasks/run.py
agent_tasks-0.1.dist-info/METADATA
agent_tasks-0.1.dist-info/WHEEL
agent_tasks-0.1.dist-info/entry_points.txt
agent_tasks-0.1.dist-info/top_level.txt
agent_tasks-0.1.dist-info/RECORD
