Metadata-Version: 2.1
Name: agent-tasks
Version: 0.1
Summary: A task package for AI Research Bench
Home-page: http://github.com/ArtifactAI/agent-tasks
Author: Algorithmic Research Group
Author-email: matt@algorithmicresearchgroup.com
Keywords: tasks,agent,benchmark
Requires-Dist: Jinja2==3.1.4
Requires-Dist: MarkupSafe==2.1.5
